{
  "version": "0.2.1",
  "defaults": {},
  "configurations": [
    {
      "type": "default",
      "project": "CMakeLists.txt",
      "projectTarget": "advent-of-code-test.exe (test\\advent-of-code-test.exe)",
      "name": "advent-of-code-test.exe (test\\advent-of-code-test.exe)",
      "args": [
        "~[slow]"
      ]
    },
    {
      "name": "advent-of-code.exe (app\\advent-of-code.exe)",
      "project": "CMakeLists.txt",
      "projectTarget": "advent-of-code.exe (app\\advent-of-code.exe)",
      "type": "default",
      "args": [
        "2020 1 ./data/2020/Day01.txt"
      ]
    }
  ]
}